fast_pagerank/__init__.py
fast_pagerank/fast_pagerank.py
fast_pagerank-0.0.4.dist-info/LICENSE
fast_pagerank-0.0.4.dist-info/METADATA
fast_pagerank-0.0.4.dist-info/WHEEL
fast_pagerank-0.0.4.dist-info/top_level.txt
fast_pagerank-0.0.4.dist-info/RECORD
