Metadata-Version: 2.1
Name: fast-pagerank
Version: 0.0.4
Summary: A fast PageRank and Personalized PageRank implementation
Home-page: https://github.com/asajadi/fast_pagerank
Author: Armin Sajadi
Author-email: asajadi@gmail.com
License: UNKNOWN
Platform: UNKNOWN
Classifier: Programming Language :: Python :: 3
Classifier: License :: OSI Approved :: MIT License
Classifier: Operating System :: OS Independent
